pythonfmu3/__init__.py
pythonfmu3/__main__.py
pythonfmu3/_version.py
pythonfmu3/builder.py
pythonfmu3/cosimulation.py
pythonfmu3/default_experiment.py
pythonfmu3/deploy.py
pythonfmu3/enums.py
pythonfmu3/fmi3slave.py
pythonfmu3/logmsg.py
pythonfmu3/modelexchange.py
pythonfmu3/osutil.py
pythonfmu3/unit.py
pythonfmu3/variable_types.py
pythonfmu3/variables.py
pythonfmu3/pythonfmu-export/.clang-format
pythonfmu3/pythonfmu-export/CMakeLists.txt
pythonfmu3/pythonfmu-export/build_unix.sh
pythonfmu3/pythonfmu-export/build_win.sh
pythonfmu3/pythonfmu-export/src/CMakeLists.txt
pythonfmu3/pythonfmu-export/src/cppfmu/cppfmu_common.hpp
pythonfmu3/pythonfmu-export/src/cppfmu/cppfmu_cs.cpp
pythonfmu3/pythonfmu-export/src/cppfmu/cppfmu_cs.hpp
pythonfmu3/pythonfmu-export/src/cppfmu/fmi_functions.cpp
pythonfmu3/pythonfmu-export/src/fmi/fmi3FunctionTypes.h
pythonfmu3/pythonfmu-export/src/fmi/fmi3Functions.h
pythonfmu3/pythonfmu-export/src/fmi/fmi3PlatformTypes.h
pythonfmu3/pythonfmu-export/src/pythonfmu/IPyState.hpp
pythonfmu3/pythonfmu-export/src/pythonfmu/PySlaveInstance.cpp
pythonfmu3/pythonfmu-export/src/pythonfmu/PySlaveInstance.hpp
pythonfmu3/pythonfmu-export/src/pythonfmu/PyState.hpp
pythonfmu3/resources/binaries/x86_64-linux/libpythonfmu-export.so
pythonfmu3/resources/binaries/x86_64-windows/pythonfmu-export.dll
pythonfmu3/tests/__init__.py
pythonfmu3/tests/conftest.py
pythonfmu3/tests/test_builder.py
pythonfmu3/tests/test_deploy.py
pythonfmu3/tests/test_docs.py
pythonfmu3/tests/test_fmi3slave.py
pythonfmu3/tests/test_integration.py
pythonfmu3/tests/test_logger.py
pythonfmu3/tests/test_multiple_fmus.py
pythonfmu3/tests/test_variables.py
pythonfmu3/tests/utils.py
pythonfmu3/tests/data/csvdemo.csv
pythonfmu3/tests/data/hello.txt
pythonfmu3/tests/slaves/PythonSlaveWithException.py
pythonfmu3/tests/slaves/localmodule.py
pythonfmu3/tests/slaves/pythonslave.py
pythonfmu3/tests/slaves/pythonslaveMX.py
pythonfmu3/tests/slaves/pythonslaveMXCS.py
pythonfmu3-0.3.4.dist-info/licenses/LICENSE
pythonfmu3-0.3.4.dist-info/METADATA
pythonfmu3-0.3.4.dist-info/WHEEL
pythonfmu3-0.3.4.dist-info/entry_points.txt
pythonfmu3-0.3.4.dist-info/top_level.txt
pythonfmu3-0.3.4.dist-info/RECORD
