Metadata-Version: 2.4
Name: pythonfmu3
Version: 0.3.4
Summary: A lightweight framework that enables the packaging of Python3.x code as co-simulation FMUs.
Home-page: https://github.com/stephensmith25/PythonFMU3
Author: Stephen Smith
License: MIT
Keywords: FMI
Classifier: Development Status :: 3 - Alpha
Classifier: Intended Audience :: End Users/Desktop
Classifier: Intended Audience :: Developers
Classifier: Intended Audience :: Science/Research
Classifier: License :: OSI Approved :: MIT License
Classifier: Natural Language :: English
Classifier: Programming Language :: C++
Classifier: Programming Language :: Python :: 3 :: Only
Classifier: Programming Language :: Python :: 3.6
Classifier: Programming Language :: Python :: 3.7
Classifier: Programming Language :: Python :: 3.8
Classifier: Topic :: Scientific/Engineering
License-File: LICENSE
Provides-Extra: tests
Requires-Dist: pytest; extra == "tests"
Requires-Dist: fmpy; extra == "tests"
Dynamic: license-file
